OptiCommPy-0.7.0.data/scripts/runner
optic/__init__.py
optic/plot.py
optic/utils.py
optic/comm/fec.py
optic/comm/metrics.py
optic/comm/modulation.py
optic/comm/ofdm.py
optic/dsp/carrierRecovery.py
optic/dsp/clockRecovery.py
optic/dsp/core.py
optic/dsp/coreGPU.py
optic/dsp/equalization.py
optic/models/amplification.py
optic/models/channels.py
optic/models/devices.py
optic/models/modelsGPU.py
optic/models/tx.py
OptiCommPy-0.7.0.dist-info/LICENSE
OptiCommPy-0.7.0.dist-info/METADATA
OptiCommPy-0.7.0.dist-info/WHEEL
OptiCommPy-0.7.0.dist-info/top_level.txt
OptiCommPy-0.7.0.dist-info/RECORD
