Metadata-Version: 2.1
Name: OptiCommPy
Version: 0.7.0
Summary: Optical Communications Algorithms with Python
Home-page: https://github.com/edsonportosilva/OptiCommPy
Maintainer: Edson Porto da Silva
Maintainer-email: edsonporto88@gmail.com
License: BSD 3-Clause
Classifier: Development Status :: 4 - Beta
Classifier: Intended Audience :: Science/Research
Classifier: Intended Audience :: Telecommunications Industry
Classifier: Operating System :: Unix
Classifier: Programming Language :: Python
Classifier: Topic :: Scientific/Engineering
Classifier: Topic :: Software Development
Requires-Python: >=3.2
License-File: LICENSE
Requires-Dist: numpy >=1.9.2
Requires-Dist: scipy >=0.15.0
Requires-Dist: matplotlib >=3.7.0
Requires-Dist: sympy
Requires-Dist: tqdm >=4.64.1
Requires-Dist: numba >=0.54.1
Requires-Dist: scikit-commpy >=0.7.0
Requires-Dist: simple-pid >=1.0.1
Requires-Dist: mpl-scatter-density >=0.7.0
Requires-Dist: pandas >=2.0.0
Requires-Dist: sphinx-rtd-theme >=1.2.2
